{
  "attributes": [
    {
      "default": "nil",
      "size": null,
      "type": "uuid",
      "source": "service_group_id",
      "references": {
        "name": "service_group_vehicles_service_group_id_fkey",
        "table": "service_groups",
        "multitenancy": {
          "global": false,
          "strategy": "context",
          "attribute": null
        },
        "primary_key?": true,
        "schema": "public",
        "destination_attribute": "id",
        "on_delete": "delete",
        "on_update": null,
        "deferrable": false,
        "match_with": null,
        "match_type": null,
        "index?": false,
        "destination_attribute_default": null,
        "destination_attribute_generated": null
      },
      "allow_nil?": false,
      "primary_key?": true,
      "generated?": false
    },
    {
      "default": "nil",
      "size": null,
      "type": "uuid",
      "source": "vehicle_id",
      "references": {
        "name": "service_group_vehicles_vehicle_id_fkey",
        "table": "vehicles",
        "multitenancy": {
          "global": false,
          "strategy": "context",
          "attribute": null
        },
        "primary_key?": true,
        "schema": "public",
        "destination_attribute": "id",
        "on_delete": "delete",
        "on_update": null,
        "deferrable": false,
        "match_with": null,
        "match_type": null,
        "index?": false,
        "destination_attribute_default": null,
        "destination_attribute_generated": null
      },
      "allow_nil?": false,
      "primary_key?": true,
      "generated?": false
    }
  ],
  "table": "service_group_vehicles",
  "hash": "8D59A56D8FBC80AAB2C113CC7112EAF057226C449DB8573C5ADF54A71DCA5B7D",
  "repo": "Elixir.Fleetms.Repo",
  "identities": [],
  "multitenancy": {
    "global": false,
    "strategy": "context",
    "attribute": null
  },
  "schema": null,
  "check_constraints": [],
  "custom_indexes": [],
  "base_filter": null,
  "custom_statements": [],
  "has_create_action": true
}